<?xml version="1.0" encoding="utf-8"?>
<!DOCTYPE hibernate-mapping PUBLIC "-//Hibernate/Hibernate Mapping DTD 3.0//EN"
"http://hibernate.sourceforge.net/hibernate-mapping-3.0.dtd">
<!-- 
    Mapping file autogenerated by MyEclipse Persistence Tools
-->
<hibernate-mapping>
    <class name="US.CPS.entity.userinfo.Userinfo" table="userinfo" catalog="cps">
        <id name="userinfoId" type="java.lang.Integer">
            <column name="userinfo_id" />
            <generator class="native" />
        </id>
        <many-to-one name="dom" class="US.CPS.entity.dom.Dom" fetch="select">
            <column name="dom_id" not-null="true" />
        </many-to-one>
        <many-to-one name="major" class="US.CPS.entity.major.Major" fetch="select">
            <column name="major_id" not-null="true" />
        </many-to-one>
        <property name="userinfoSign" type="java.lang.String">
            <column name="userinfo_sign" length="400" />
        </property>
        <property name="userinfoRegisterTime" type="java.sql.Timestamp">
            <column name="userinfo_register_time" length="19" not-null="true" />
        </property>
        <property name="userinfoLastLoginTime" type="java.sql.Timestamp">
            <column name="userinfo_last_login_time" length="19" not-null="true" />
        </property>
        <property name="userinfoLastLoginIp" type="java.lang.String">
            <column name="userinfo_last_login_ip" length="20" not-null="true" />
        </property>
        <property name="userinfoStatus" type="java.lang.Integer">
            <column name="userinfo_status" not-null="true" />
        </property>
        <set name="accounts" inverse="true">
            <key>
                <column name="userinfo_id" />
            </key>
            <one-to-many class="US.CPS.entity.account.Account" />
        </set>
    </class>
</hibernate-mapping>
